XStatic_roboto_fontface-0.5.0.0-py2.7-nspkg.pth
XStatic_roboto_fontface-0.5.0.0.dist-info/DESCRIPTION.rst
XStatic_roboto_fontface-0.5.0.0.dist-info/METADATA
XStatic_roboto_fontface-0.5.0.0.dist-info/RECORD
XStatic_roboto_fontface-0.5.0.0.dist-info/WHEEL
XStatic_roboto_fontface-0.5.0.0.dist-info/metadata.json
XStatic_roboto_fontface-0.5.0.0.dist-info/namespace_packages.txt
XStatic_roboto_fontface-0.5.0.0.dist-info/top_level.txt
xstatic/pkg/roboto_fontface/__init__.py
xstatic/pkg/roboto_fontface/data/LICENSE
xstatic/pkg/roboto_fontface/data/README.md
xstatic/pkg/roboto_fontface/data/css/mixins.less
xstatic/pkg/roboto_fontface/data/css/mixins.scss
xstatic/pkg/roboto_fontface/data/css/roboto/roboto-fontface.css
xstatic/pkg/roboto_fontface/data/css/roboto/less/roboto-fontface-black-italic.less
xstatic/pkg/roboto_fontface/data/css/roboto/less/roboto-fontface-black.less
xstatic/pkg/roboto_fontface/data/css/roboto/less/roboto-fontface-bold-italic.less
xstatic/pkg/roboto_fontface/data/css/roboto/less/roboto-fontface-bold.less
xstatic/pkg/roboto_fontface/data/css/roboto/less/roboto-fontface-light-italic.less
xstatic/pkg/roboto_fontface/data/css/roboto/less/roboto-fontface-light.less
xstatic/pkg/roboto_fontface/data/css/roboto/less/roboto-fontface-medium-italic.less
xstatic/pkg/roboto_fontface/data/css/roboto/less/roboto-fontface-medium.less
xstatic/pkg/roboto_fontface/data/css/roboto/less/roboto-fontface-regular-italic.less
xstatic/pkg/roboto_fontface/data/css/roboto/less/roboto-fontface-regular.less
xstatic/pkg/roboto_fontface/data/css/roboto/less/roboto-fontface-thin-italic.less
xstatic/pkg/roboto_fontface/data/css/roboto/less/roboto-fontface-thin.less
xstatic/pkg/roboto_fontface/data/css/roboto/less/roboto-fontface.less
xstatic/pkg/roboto_fontface/data/css/roboto/sass/roboto-fontface-black-italic.scss
xstatic/pkg/roboto_fontface/data/css/roboto/sass/roboto-fontface-black.scss
xstatic/pkg/roboto_fontface/data/css/roboto/sass/roboto-fontface-bold-italic.scss
xstatic/pkg/roboto_fontface/data/css/roboto/sass/roboto-fontface-bold.scss
xstatic/pkg/roboto_fontface/data/css/roboto/sass/roboto-fontface-light-italic.scss
xstatic/pkg/roboto_fontface/data/css/roboto/sass/roboto-fontface-light.scss
xstatic/pkg/roboto_fontface/data/css/roboto/sass/roboto-fontface-medium-italic.scss
