Metadata-Version: 2.0
Name: XStatic-roboto-fontface
Version: 0.5.0.0
Summary: roboto-fontface 0.5.0 (XStatic packaging standard)
Home-page: https://github.com/choffmeister/roboto-fontface-bower
Author: Rob Cresswell
Author-email: robert.cresswell@outlook.com
License: Apache-2.0
Keywords: roboto_fontface xstatic
Platform: any
